{
  "prop_type": "RA",
  "n_features": 23,
  "feature_names": [
    "ra_avg_3",
    "ra_avg_5",
    "ra_avg_10",
    "reb_avg_season",
    "ast_avg_season",
    "reb_volatility",
    "ast_volatility",
    "min_avg_10",
    "is_home",
    "reb_hot_streak",
    "ast_hot_streak",
    "days_rest",
    "is_back_to_back",
    "games_in_last_week",
    "win_streak",
    "loss_streak",
    "recent_win_pct",
    "reb_momentum",
    "min_std_10",
    "min_trend",
    "plus_minus_avg_10",
    "reb_per_min_10",
    "reb_hit_rate"
  ],
  "features_schema_hash": "36f6889a04c2",
  "train_samples": 24087,
  "val_samples": 5162,
  "test_samples": 5162,
  "retrain_rows": 0,
  "train_mae": 2.4779562950134277,
  "train_rmse": 3.169625974184201,
  "val_mae": 2.715421199798584,
  "val_rmse": 3.515606689405441,
  "test_mae": 2.6450624465942383,
  "test_rmse": 3.394487703349134,
  "best_iteration": 40,
  "model_type": "xgboost",
  "training_mode": "full",
  "promoted": true,
  "promotion_reason": "no_existing_model",
  "current_test_mae": null
}